easymlmodule_v1/__init__.py
esml_module_v1-0.0.1.dist-info/LICENSE
esml_module_v1-0.0.1.dist-info/METADATA
esml_module_v1-0.0.1.dist-info/WHEEL
esml_module_v1-0.0.1.dist-info/top_level.txt
esml_module_v1-0.0.1.dist-info/RECORD
