Metadata-Version: 2.1
Name: esml-module-v1
Version: 0.0.1
Summary: with help of this packeg image processsing code can be written in just two lines
Home-page: https://github.com/ultimus11/easy_ml_module
Author: sahil panindre
Author-email: sahil11panindre@gmail.com
License: UNKNOWN
Platform: UNKNOWN
Classifier: Programming Language :: Python :: 3
Classifier: License :: OSI Approved :: MIT License
Classifier: Operating System :: OS Independent
